{"nodes": [{"id": "06_agents_supervisor_py", "label": "supervisor.py", "file_type": "code", "source_file": "06_AGENTS/supervisor.py", "source_location": "L1"}, {"id": "06_agents_supervisor_canon_hash", "label": "_canon_hash()", "file_type": "code", "source_file": "06_AGENTS/supervisor.py", "source_location": "L36"}, {"id": "str", "label": "str", "file_type": "code", "source_file": "06_AGENTS/supervisor.py", "source_location": "L36"}, {"id": "06_agents_supervisor_scan_injection", "label": "scan_injection()", "file_type": "code", "source_file": "06_AGENTS/supervisor.py", "source_location": "L40"}, {"id": "bool", "label": "bool", "file_type": "code", "source_file": "06_AGENTS/supervisor.py", "source_location": "L40"}, {"id": "06_agents_supervisor_supervisorkernel", "label": "SupervisorKernel", "file_type": "code", "source_file": "06_AGENTS/supervisor.py", "source_location": "L47"}, {"id": "06_agents_supervisor_supervisorkernel_create_session", "label": ".create_session()", "file_type": "code", "source_file": "06_AGENTS/supervisor.py", "source_location": "L54"}, {"id": "asyncsession", "label": "AsyncSession", "file_type": "code", "source_file": "06_AGENTS/supervisor.py", "source_location": "L54"}, {"id": "float", "label": "float", "file_type": "code", "source_file": "06_AGENTS/supervisor.py", "source_location": "L54"}, {"id": "any", "label": "Any", "file_type": "code", "source_file": "06_AGENTS/supervisor.py", "source_location": "L54"}, {"id": "06_agents_supervisor_supervisorkernel_get_session", "label": ".get_session()", "file_type": "code", "source_file": "06_AGENTS/supervisor.py", "source_location": "L84"}, {"id": "06_agents_supervisor_supervisorkernel_append_turn", "label": ".append_turn()", "file_type": "code", "source_file": "06_AGENTS/supervisor.py", "source_location": "L93"}, {"id": "int", "label": "int", "file_type": "code", "source_file": "06_AGENTS/supervisor.py", "source_location": "L93"}, {"id": "06_agents_supervisor_supervisorkernel_get_history", "label": ".get_history()", "file_type": "code", "source_file": "06_AGENTS/supervisor.py", "source_location": "L150"}, {"id": "06_agents_supervisor_supervisorkernel_heal_turn", "label": ".heal_turn()", "file_type": "code", "source_file": "06_AGENTS/supervisor.py", "source_location": "L166"}, {"id": "06_agents_supervisor_supervisorkernel_audit_session", "label": ".audit_session()", "file_type": "code", "source_file": "06_AGENTS/supervisor.py", "source_location": "L203"}, {"id": "06_agents_supervisor_rationale_1", "label": "Supervisor Kernel \u2014 Canonical session management, injection filtering, self-heal", "file_type": "rationale", "source_file": "06_AGENTS/supervisor.py", "source_location": "L1"}, {"id": "06_agents_supervisor_rationale_41", "label": "Return (cleaned_text, injection_detected).", "file_type": "rationale", "source_file": "06_AGENTS/supervisor.py", "source_location": "L41"}, {"id": "06_agents_supervisor_rationale_48", "label": "Mediates all AI session state. Enforces Canon Lock invariants.     All session m", "file_type": "rationale", "source_file": "06_AGENTS/supervisor.py", "source_location": "L48"}, {"id": "06_agents_supervisor_rationale_100", "label": "Append a new turn. Scans all text parts for injection attacks.         Returns t", "file_type": "rationale", "source_file": "06_AGENTS/supervisor.py", "source_location": "L100"}, {"id": "06_agents_supervisor_rationale_174", "label": "Replace a turn's parts with corrected content and mark is_healed=True.         W", "file_type": "rationale", "source_file": "06_AGENTS/supervisor.py", "source_location": "L174"}, {"id": "06_agents_supervisor_rationale_204", "label": "Audit a session for injection evidence and unhealed anomalies.", "file_type": "rationale", "source_file": "06_AGENTS/supervisor.py", "source_location": "L204"}], "edges": [{"source": "06_agents_supervisor_py", "target": "hashlib", "relation": "imports", "context": "import", "confidence": "EXTRACTED", "source_file": "06_AGENTS/supervisor.py", "source_location": "L8", "weight": 1.0}, {"source": "06_agents_supervisor_py", "target": "json", "relation": "imports", "context": "import", "confidence": "EXTRACTED", "source_file": "06_AGENTS/supervisor.py", "source_location": "L9", "weight": 1.0}, {"source": "06_agents_supervisor_py", "target": "logging", "relation": "imports", "context": "import", "confidence": "EXTRACTED", "source_file": "06_AGENTS/supervisor.py", "source_location": "L10", "weight": 1.0}, {"source": "06_agents_supervisor_py", "target": "re", "relation": "imports", "context": "import", "confidence": "EXTRACTED", "source_file": "06_AGENTS/supervisor.py", "source_location": "L11", "weight": 1.0}, {"source": "06_agents_supervisor_py", "target": "datetime", "relation": "imports_from", "context": "import", "confidence": "EXTRACTED", "source_file": "06_AGENTS/supervisor.py", "source_location": "L12", "weight": 1.0}, {"source": "06_agents_supervisor_py", "target": "typing", "relation": "imports_from", "context": "import", "confidence": "EXTRACTED", "source_file": "06_AGENTS/supervisor.py", "source_location": "L13", "weight": 1.0}, {"source": "06_agents_supervisor_py", "target": "sqlalchemy", "relation": "imports_from", "context": "import", "confidence": "EXTRACTED", "source_file": "06_AGENTS/supervisor.py", "source_location": "L15", "weight": 1.0}, {"source": "06_agents_supervisor_py", "target": "sqlalchemy_ext_asyncio", "relation": "imports_from", "context": "import", "confidence": "EXTRACTED", "source_file": "06_AGENTS/supervisor.py", "source_location": "L16", "weight": 1.0}, {"source": "06_agents_supervisor_py", "target": "config_py", "relation": "imports_from", "context": "import", "confidence": "EXTRACTED", "source_file": "06_AGENTS/supervisor.py", "source_location": "L18", "weight": 1.0}, {"source": "06_agents_supervisor_py", "target": "06_agents_supervisor_canon_hash", "relation": "contains", "confidence": "EXTRACTED", "source_file": "06_AGENTS/supervisor.py", "source_location": "L36", "weight": 1.0}, {"source": "06_agents_supervisor_canon_hash", "target": "str", "relation": "references", "context": "parameter_type", "confidence": "EXTRACTED", "source_file": "06_AGENTS/supervisor.py", "source_location": "L36", "weight": 1.0}, {"source": "06_agents_supervisor_canon_hash", "target": "str", "relation": "references", "context": "return_type", "confidence": "EXTRACTED", "source_file": "06_AGENTS/supervisor.py", "source_location": "L36", "weight": 1.0}, {"source": "06_agents_supervisor_py", "target": "06_agents_supervisor_scan_injection", "relation": "contains", "confidence": "EXTRACTED", "source_file": "06_AGENTS/supervisor.py", "source_location": "L40", "weight": 1.0}, {"source": "06_agents_supervisor_scan_injection", "target": "str", "relation": "references", "context": "parameter_type", "confidence": "EXTRACTED", "source_file": "06_AGENTS/supervisor.py", "source_location": "L40", "weight": 1.0}, {"source": "06_agents_supervisor_scan_injection", "target": "str", "relation": "references", "context": "generic_arg", "confidence": "EXTRACTED", "source_file": "06_AGENTS/supervisor.py", "source_location": "L40", "weight": 1.0}, {"source": "06_agents_supervisor_scan_injection", "target": "bool", "relation": "references", "context": "generic_arg", "confidence": "EXTRACTED", "source_file": "06_AGENTS/supervisor.py", "source_location": "L40", "weight": 1.0}, {"source": "06_agents_supervisor_py", "target": "06_agents_supervisor_supervisorkernel", "relation": "contains", "confidence": "EXTRACTED", "source_file": "06_AGENTS/supervisor.py", "source_location": "L47", "weight": 1.0}, {"source": "06_agents_supervisor_supervisorkernel", "target": "06_agents_supervisor_supervisorkernel_create_session", "relation": "method", "confidence": "EXTRACTED", "source_file": "06_AGENTS/supervisor.py", "source_location": "L54", "weight": 1.0}, {"source": "06_agents_supervisor_supervisorkernel_create_session", "target": "asyncsession", "relation": "references", "context": "parameter_type", "confidence": "EXTRACTED", "source_file": "06_AGENTS/supervisor.py", "source_location": "L54", "weight": 1.0}, {"source": "06_agents_supervisor_supervisorkernel_create_session", "target": "str", "relation": "references", "context": "parameter_type", "confidence": "EXTRACTED", "source_file": "06_AGENTS/supervisor.py", "source_location": "L54", "weight": 1.0}, {"source": "06_agents_supervisor_supervisorkernel_create_session", "target": "str", "relation": "references", "context": "parameter_type", "confidence": "EXTRACTED", "source_file": "06_AGENTS/supervisor.py", "source_location": "L54", "weight": 1.0}, {"source": "06_agents_supervisor_supervisorkernel_create_session", "target": "str", "relation": "references", "context": "parameter_type", "confidence": "EXTRACTED", "source_file": "06_AGENTS/supervisor.py", "source_location": "L54", "weight": 1.0}, {"source": "06_agents_supervisor_supervisorkernel_create_session", "target": "str", "relation": "references", "context": "parameter_type", "confidence": "EXTRACTED", "source_file": "06_AGENTS/supervisor.py", "source_location": "L54", "weight": 1.0}, {"source": "06_agents_supervisor_supervisorkernel_create_session", "target": "float", "relation": "references", "context": "parameter_type", "confidence": "EXTRACTED", "source_file": "06_AGENTS/supervisor.py", "source_location": "L54", "weight": 1.0}, {"source": "06_agents_supervisor_supervisorkernel_create_session", "target": "str", "relation": "references", "context": "generic_arg", "confidence": "EXTRACTED", "source_file": "06_AGENTS/supervisor.py", "source_location": "L54", "weight": 1.0}, {"source": "06_agents_supervisor_supervisorkernel_create_session", "target": "any", "relation": "references", "context": "generic_arg", "confidence": "EXTRACTED", "source_file": "06_AGENTS/supervisor.py", "source_location": "L54", "weight": 1.0}, {"source": "06_agents_supervisor_supervisorkernel", "target": "06_agents_supervisor_supervisorkernel_get_session", "relation": "method", "confidence": "EXTRACTED", "source_file": "06_AGENTS/supervisor.py", "source_location": "L84", "weight": 1.0}, {"source": "06_agents_supervisor_supervisorkernel_get_session", "target": "asyncsession", "relation": "references", "context": "parameter_type", "confidence": "EXTRACTED", "source_file": "06_AGENTS/supervisor.py", "source_location": "L84", "weight": 1.0}, {"source": "06_agents_supervisor_supervisorkernel_get_session", "target": "str", "relation": "references", "context": "parameter_type", "confidence": "EXTRACTED", "source_file": "06_AGENTS/supervisor.py", "source_location": "L84", "weight": 1.0}, {"source": "06_agents_supervisor_supervisorkernel", "target": "06_agents_supervisor_supervisorkernel_append_turn", "relation": "method", "confidence": "EXTRACTED", "source_file": "06_AGENTS/supervisor.py", "source_location": "L93", "weight": 1.0}, {"source": "06_agents_supervisor_supervisorkernel_append_turn", "target": "asyncsession", "relation": "references", "context": "parameter_type", "confidence": "EXTRACTED", "source_file": "06_AGENTS/supervisor.py", "source_location": "L93", "weight": 1.0}, {"source": "06_agents_supervisor_supervisorkernel_append_turn", "target": "str", "relation": "references", "context": "parameter_type", "confidence": "EXTRACTED", "source_file": "06_AGENTS/supervisor.py", "source_location": "L93", "weight": 1.0}, {"source": "06_agents_supervisor_supervisorkernel_append_turn", "target": "str", "relation": "references", "context": "parameter_type", "confidence": "EXTRACTED", "source_file": "06_AGENTS/supervisor.py", "source_location": "L93", "weight": 1.0}, {"source": "06_agents_supervisor_supervisorkernel_append_turn", "target": "str", "relation": "references", "context": "generic_arg", "confidence": "EXTRACTED", "source_file": "06_AGENTS/supervisor.py", "source_location": "L93", "weight": 1.0}, {"source": "06_agents_supervisor_supervisorkernel_append_turn", "target": "any", "relation": "references", "context": "generic_arg", "confidence": "EXTRACTED", "source_file": "06_AGENTS/supervisor.py", "source_location": "L93", "weight": 1.0}, {"source": "06_agents_supervisor_supervisorkernel_append_turn", "target": "int", "relation": "references", "context": "return_type", "confidence": "EXTRACTED", "source_file": "06_AGENTS/supervisor.py", "source_location": "L93", "weight": 1.0}, {"source": "06_agents_supervisor_supervisorkernel", "target": "06_agents_supervisor_supervisorkernel_get_history", "relation": "method", "confidence": "EXTRACTED", "source_file": "06_AGENTS/supervisor.py", "source_location": "L150", "weight": 1.0}, {"source": "06_agents_supervisor_supervisorkernel_get_history", "target": "asyncsession", "relation": "references", "context": "parameter_type", "confidence": "EXTRACTED", "source_file": "06_AGENTS/supervisor.py", "source_location": "L150", "weight": 1.0}, {"source": "06_agents_supervisor_supervisorkernel_get_history", "target": "str", "relation": "references", "context": "parameter_type", "confidence": "EXTRACTED", "source_file": "06_AGENTS/supervisor.py", "source_location": "L150", "weight": 1.0}, {"source": "06_agents_supervisor_supervisorkernel_get_history", "target": "int", "relation": "references", "context": "parameter_type", "confidence": "EXTRACTED", "source_file": "06_AGENTS/supervisor.py", "source_location": "L150", "weight": 1.0}, {"source": "06_agents_supervisor_supervisorkernel_get_history", "target": "str", "relation": "references", "context": "generic_arg", "confidence": "EXTRACTED", "source_file": "06_AGENTS/supervisor.py", "source_location": "L150", "weight": 1.0}, {"source": "06_agents_supervisor_supervisorkernel_get_history", "target": "any", "relation": "references", "context": "generic_arg", "confidence": "EXTRACTED", "source_file": "06_AGENTS/supervisor.py", "source_location": "L150", "weight": 1.0}, {"source": "06_agents_supervisor_supervisorkernel", "target": "06_agents_supervisor_supervisorkernel_heal_turn", "relation": "method", "confidence": "EXTRACTED", "source_file": "06_AGENTS/supervisor.py", "source_location": "L166", "weight": 1.0}, {"source": "06_agents_supervisor_supervisorkernel_heal_turn", "target": "asyncsession", "relation": "references", "context": "parameter_type", "confidence": "EXTRACTED", "source_file": "06_AGENTS/supervisor.py", "source_location": "L166", "weight": 1.0}, {"source": "06_agents_supervisor_supervisorkernel_heal_turn", "target": "str", "relation": "references", "context": "parameter_type", "confidence": "EXTRACTED", "source_file": "06_AGENTS/supervisor.py", "source_location": "L166", "weight": 1.0}, {"source": "06_agents_supervisor_supervisorkernel_heal_turn", "target": "int", "relation": "references", "context": "parameter_type", "confidence": "EXTRACTED", "source_file": "06_AGENTS/supervisor.py", "source_location": "L166", "weight": 1.0}, {"source": "06_agents_supervisor_supervisorkernel_heal_turn", "target": "str", "relation": "references", "context": "parameter_type", "confidence": "EXTRACTED", "source_file": "06_AGENTS/supervisor.py", "source_location": "L166", "weight": 1.0}, {"source": "06_agents_supervisor_supervisorkernel_heal_turn", "target": "str", "relation": "references", "context": "generic_arg", "confidence": "EXTRACTED", "source_file": "06_AGENTS/supervisor.py", "source_location": "L166", "weight": 1.0}, {"source": "06_agents_supervisor_supervisorkernel_heal_turn", "target": "any", "relation": "references", "context": "generic_arg", "confidence": "EXTRACTED", "source_file": "06_AGENTS/supervisor.py", "source_location": "L166", "weight": 1.0}, {"source": "06_agents_supervisor_supervisorkernel_heal_turn", "target": "bool", "relation": "references", "context": "return_type", "confidence": "EXTRACTED", "source_file": "06_AGENTS/supervisor.py", "source_location": "L166", "weight": 1.0}, {"source": "06_agents_supervisor_supervisorkernel", "target": "06_agents_supervisor_supervisorkernel_audit_session", "relation": "method", "confidence": "EXTRACTED", "source_file": "06_AGENTS/supervisor.py", "source_location": "L203", "weight": 1.0}, {"source": "06_agents_supervisor_supervisorkernel_audit_session", "target": "asyncsession", "relation": "references", "context": "parameter_type", "confidence": "EXTRACTED", "source_file": "06_AGENTS/supervisor.py", "source_location": "L203", "weight": 1.0}, {"source": "06_agents_supervisor_supervisorkernel_audit_session", "target": "str", "relation": "references", "context": "parameter_type", "confidence": "EXTRACTED", "source_file": "06_AGENTS/supervisor.py", "source_location": "L203", "weight": 1.0}, {"source": "06_agents_supervisor_supervisorkernel_audit_session", "target": "str", "relation": "references", "context": "generic_arg", "confidence": "EXTRACTED", "source_file": "06_AGENTS/supervisor.py", "source_location": "L203", "weight": 1.0}, {"source": "06_agents_supervisor_supervisorkernel_audit_session", "target": "any", "relation": "references", "context": "generic_arg", "confidence": "EXTRACTED", "source_file": "06_AGENTS/supervisor.py", "source_location": "L203", "weight": 1.0}, {"source": "06_agents_supervisor_scan_injection", "target": "bool", "relation": "calls", "context": "call", "confidence": "EXTRACTED", "source_file": "06_AGENTS/supervisor.py", "source_location": "L42", "weight": 1.0}, {"source": "06_agents_supervisor_supervisorkernel_append_turn", "target": "06_agents_supervisor_scan_injection", "relation": "calls", "context": "call", "confidence": "EXTRACTED", "source_file": "06_AGENTS/supervisor.py", "source_location": "L108", "weight": 1.0}, {"source": "06_agents_supervisor_supervisorkernel_append_turn", "target": "int", "relation": "calls", "context": "call", "confidence": "EXTRACTED", "source_file": "06_AGENTS/supervisor.py", "source_location": "L124", "weight": 1.0}, {"source": "06_agents_supervisor_supervisorkernel_audit_session", "target": "06_agents_supervisor_supervisorkernel_get_history", "relation": "calls", "context": "call", "confidence": "EXTRACTED", "source_file": "06_AGENTS/supervisor.py", "source_location": "L205", "weight": 1.0}, {"source": "06_agents_supervisor_supervisorkernel_audit_session", "target": "06_agents_supervisor_scan_injection", "relation": "calls", "context": "call", "confidence": "EXTRACTED", "source_file": "06_AGENTS/supervisor.py", "source_location": "L213", "weight": 1.0}, {"source": "06_agents_supervisor_rationale_1", "target": "06_agents_supervisor_py", "relation": "rationale_for", "confidence": "EXTRACTED", "source_file": "06_AGENTS/supervisor.py", "source_location": "L1", "weight": 1.0}, {"source": "06_agents_supervisor_rationale_41", "target": "06_agents_supervisor_scan_injection", "relation": "rationale_for", "confidence": "EXTRACTED", "source_file": "06_AGENTS/supervisor.py", "source_location": "L41", "weight": 1.0}, {"source": "06_agents_supervisor_rationale_48", "target": "06_agents_supervisor_supervisorkernel", "relation": "rationale_for", "confidence": "EXTRACTED", "source_file": "06_AGENTS/supervisor.py", "source_location": "L48", "weight": 1.0}, {"source": "06_agents_supervisor_rationale_100", "target": "06_agents_supervisor_supervisorkernel_append_turn", "relation": "rationale_for", "confidence": "EXTRACTED", "source_file": "06_AGENTS/supervisor.py", "source_location": "L100", "weight": 1.0}, {"source": "06_agents_supervisor_rationale_174", "target": "06_agents_supervisor_supervisorkernel_heal_turn", "relation": "rationale_for", "confidence": "EXTRACTED", "source_file": "06_AGENTS/supervisor.py", "source_location": "L174", "weight": 1.0}, {"source": "06_agents_supervisor_rationale_204", "target": "06_agents_supervisor_supervisorkernel_audit_session", "relation": "rationale_for", "confidence": "EXTRACTED", "source_file": "06_AGENTS/supervisor.py", "source_location": "L204", "weight": 1.0}], "raw_calls": [{"caller_nid": "06_agents_supervisor_canon_hash", "callee": "hexdigest", "is_member_call": true, "source_file": "06_AGENTS/supervisor.py", "source_location": "L37"}, {"caller_nid": "06_agents_supervisor_canon_hash", "callee": "sha256", "is_member_call": true, "source_file": "06_AGENTS/supervisor.py", "source_location": "L37"}, {"caller_nid": "06_agents_supervisor_canon_hash", "callee": "encode", "is_member_call": true, "source_file": "06_AGENTS/supervisor.py", "source_location": "L37"}, {"caller_nid": "06_agents_supervisor_scan_injection", "callee": "search", "is_member_call": true, "source_file": "06_AGENTS/supervisor.py", "source_location": "L42"}, {"caller_nid": "06_agents_supervisor_scan_injection", "callee": "sub", "is_member_call": true, "source_file": "06_AGENTS/supervisor.py", "source_location": "L43"}, {"caller_nid": "06_agents_supervisor_supervisorkernel_create_session", "callee": "text", "is_member_call": false, "source_file": "06_AGENTS/supervisor.py", "source_location": "L63"}, {"caller_nid": "06_agents_supervisor_supervisorkernel_create_session", "callee": "execute", "is_member_call": true, "source_file": "06_AGENTS/supervisor.py", "source_location": "L73"}, {"caller_nid": "06_agents_supervisor_supervisorkernel_create_session", "callee": "dict", "is_member_call": false, "source_file": "06_AGENTS/supervisor.py", "source_location": "L73"}, {"caller_nid": "06_agents_supervisor_supervisorkernel_create_session", "callee": "commit", "is_member_call": true, "source_file": "06_AGENTS/supervisor.py", "source_location": "L81"}, {"caller_nid": "06_agents_supervisor_supervisorkernel_create_session", "callee": "dict", "is_member_call": false, "source_file": "06_AGENTS/supervisor.py", "source_location": "L82"}, {"caller_nid": "06_agents_supervisor_supervisorkernel_create_session", "callee": "first", "is_member_call": true, "source_file": "06_AGENTS/supervisor.py", "source_location": "L82"}, {"caller_nid": "06_agents_supervisor_supervisorkernel_create_session", "callee": "mappings", "is_member_call": true, "source_file": "06_AGENTS/supervisor.py", "source_location": "L82"}, {"caller_nid": "06_agents_supervisor_supervisorkernel_get_session", "callee": "execute", "is_member_call": true, "source_file": "06_AGENTS/supervisor.py", "source_location": "L85"}, {"caller_nid": "06_agents_supervisor_supervisorkernel_get_session", "callee": "text", "is_member_call": false, "source_file": "06_AGENTS/supervisor.py", "source_location": "L86"}, {"caller_nid": "06_agents_supervisor_supervisorkernel_get_session", "callee": "first", "is_member_call": true, "source_file": "06_AGENTS/supervisor.py", "source_location": "L89"}, {"caller_nid": "06_agents_supervisor_supervisorkernel_get_session", "callee": "mappings", "is_member_call": true, "source_file": "06_AGENTS/supervisor.py", "source_location": "L89"}, {"caller_nid": "06_agents_supervisor_supervisorkernel_get_session", "callee": "dict", "is_member_call": false, "source_file": "06_AGENTS/supervisor.py", "source_location": "L90"}, {"caller_nid": "06_agents_supervisor_supervisorkernel_append_turn", "callee": "warning", "is_member_call": true, "source_file": "06_AGENTS/supervisor.py", "source_location": "L111"}, {"caller_nid": "06_agents_supervisor_supervisorkernel_append_turn", "callee": "append", "is_member_call": true, "source_file": "06_AGENTS/supervisor.py", "source_location": "L115"}, {"caller_nid": "06_agents_supervisor_supervisorkernel_append_turn", "callee": "append", "is_member_call": true, "source_file": "06_AGENTS/supervisor.py", "source_location": "L117"}, {"caller_nid": "06_agents_supervisor_supervisorkernel_append_turn", "callee": "execute", "is_member_call": true, "source_file": "06_AGENTS/supervisor.py", "source_location": "L120"}, {"caller_nid": "06_agents_supervisor_supervisorkernel_append_turn", "callee": "text", "is_member_call": false, "source_file": "06_AGENTS/supervisor.py", "source_location": "L121"}, {"caller_nid": "06_agents_supervisor_supervisorkernel_append_turn", "callee": "scalar_one", "is_member_call": true, "source_file": "06_AGENTS/supervisor.py", "source_location": "L124"}, {"caller_nid": "06_agents_supervisor_supervisorkernel_append_turn", "callee": "text", "is_member_call": false, "source_file": "06_AGENTS/supervisor.py", "source_location": "L126"}, {"caller_nid": "06_agents_supervisor_supervisorkernel_append_turn", "callee": "any", "is_member_call": false, "source_file": "06_AGENTS/supervisor.py", "source_location": "L133"}, {"caller_nid": "06_agents_supervisor_supervisorkernel_append_turn", "callee": "get", "is_member_call": true, "source_file": "06_AGENTS/supervisor.py", "source_location": "L133"}, {"caller_nid": "06_agents_supervisor_supervisorkernel_append_turn", "callee": "execute", "is_member_call": true, "source_file": "06_AGENTS/supervisor.py", "source_location": "L134"}, {"caller_nid": "06_agents_supervisor_supervisorkernel_append_turn", "callee": "dict", "is_member_call": false, "source_file": "06_AGENTS/supervisor.py", "source_location": "L134"}, {"caller_nid": "06_agents_supervisor_supervisorkernel_append_turn", "callee": "dumps", "is_member_call": true, "source_file": "06_AGENTS/supervisor.py", "source_location": "L138"}, {"caller_nid": "06_agents_supervisor_supervisorkernel_append_turn", "callee": "execute", "is_member_call": true, "source_file": "06_AGENTS/supervisor.py", "source_location": "L143"}, {"caller_nid": "06_agents_supervisor_supervisorkernel_append_turn", "callee": "text", "is_member_call": false, "source_file": "06_AGENTS/supervisor.py", "source_location": "L144"}, {"caller_nid": "06_agents_supervisor_supervisorkernel_append_turn", "callee": "commit", "is_member_call": true, "source_file": "06_AGENTS/supervisor.py", "source_location": "L147"}, {"caller_nid": "06_agents_supervisor_supervisorkernel_get_history", "callee": "execute", "is_member_call": true, "source_file": "06_AGENTS/supervisor.py", "source_location": "L153"}, {"caller_nid": "06_agents_supervisor_supervisorkernel_get_history", "callee": "text", "is_member_call": false, "source_file": "06_AGENTS/supervisor.py", "source_location": "L154"}, {"caller_nid": "06_agents_supervisor_supervisorkernel_get_history", "callee": "dict", "is_member_call": false, "source_file": "06_AGENTS/supervisor.py", "source_location": "L163"}, {"caller_nid": "06_agents_supervisor_supervisorkernel_get_history", "callee": "all", "is_member_call": true, "source_file": "06_AGENTS/supervisor.py", "source_location": "L163"}, {"caller_nid": "06_agents_supervisor_supervisorkernel_get_history", "callee": "mappings", "is_member_call": true, "source_file": "06_AGENTS/supervisor.py", "source_location": "L163"}, {"caller_nid": "06_agents_supervisor_supervisorkernel_heal_turn", "callee": "text", "is_member_call": false, "source_file": "06_AGENTS/supervisor.py", "source_location": "L178"}, {"caller_nid": "06_agents_supervisor_supervisorkernel_heal_turn", "callee": "execute", "is_member_call": true, "source_file": "06_AGENTS/supervisor.py", "source_location": "L184"}, {"caller_nid": "06_agents_supervisor_supervisorkernel_heal_turn", "callee": "dict", "is_member_call": false, "source_file": "06_AGENTS/supervisor.py", "source_location": "L184"}, {"caller_nid": "06_agents_supervisor_supervisorkernel_heal_turn", "callee": "dumps", "is_member_call": true, "source_file": "06_AGENTS/supervisor.py", "source_location": "L185"}, {"caller_nid": "06_agents_supervisor_supervisorkernel_heal_turn", "callee": "execute", "is_member_call": true, "source_file": "06_AGENTS/supervisor.py", "source_location": "L192"}, {"caller_nid": "06_agents_supervisor_supervisorkernel_heal_turn", "callee": "text", "is_member_call": false, "source_file": "06_AGENTS/supervisor.py", "source_location": "L192"}, {"caller_nid": "06_agents_supervisor_supervisorkernel_heal_turn", "callee": "commit", "is_member_call": true, "source_file": "06_AGENTS/supervisor.py", "source_location": "L198"}, {"caller_nid": "06_agents_supervisor_supervisorkernel_heal_turn", "callee": "info", "is_member_call": true, "source_file": "06_AGENTS/supervisor.py", "source_location": "L199"}, {"caller_nid": "06_agents_supervisor_supervisorkernel_audit_session", "callee": "get", "is_member_call": true, "source_file": "06_AGENTS/supervisor.py", "source_location": "L208"}, {"caller_nid": "06_agents_supervisor_supervisorkernel_audit_session", "callee": "isinstance", "is_member_call": false, "source_file": "06_AGENTS/supervisor.py", "source_location": "L209"}, {"caller_nid": "06_agents_supervisor_supervisorkernel_audit_session", "callee": "loads", "is_member_call": true, "source_file": "06_AGENTS/supervisor.py", "source_location": "L210"}, {"caller_nid": "06_agents_supervisor_supervisorkernel_audit_session", "callee": "get", "is_member_call": true, "source_file": "06_AGENTS/supervisor.py", "source_location": "L212"}, {"caller_nid": "06_agents_supervisor_supervisorkernel_audit_session", "callee": "get", "is_member_call": true, "source_file": "06_AGENTS/supervisor.py", "source_location": "L214"}, {"caller_nid": "06_agents_supervisor_supervisorkernel_audit_session", "callee": "append", "is_member_call": true, "source_file": "06_AGENTS/supervisor.py", "source_location": "L215"}, {"caller_nid": "06_agents_supervisor_supervisorkernel_audit_session", "callee": "len", "is_member_call": false, "source_file": "06_AGENTS/supervisor.py", "source_location": "L223"}, {"caller_nid": "06_agents_supervisor_supervisorkernel_audit_session", "callee": "isoformat", "is_member_call": true, "source_file": "06_AGENTS/supervisor.py", "source_location": "L226"}, {"caller_nid": "06_agents_supervisor_supervisorkernel_audit_session", "callee": "now", "is_member_call": true, "source_file": "06_AGENTS/supervisor.py", "source_location": "L226"}]}